{
    "openapi": "3.0.1",
    "info": {
        "title": "spot",
        "description": "spot_public",
        "version": "1.0.0"
    },
    "tags": [],
    "paths": {
        "/ticker/market/ticker:_symbol_,_symbol_": {
            "trace": {
                "summary": "Get Ticker",
                "deprecated": "false",
                "description": "Subscribe to this topic to get the specified symbol push of BBO changes.",
                "tags": [],
                "parameters": [],
                "x-sdk-service": "Spot",
                "x-sdk-sub-service": "spot_public",
                "x-sdk-private": false,
                "x-sdk-method-name": "ticker",
                "x-topic": "/market/ticker:{symbol},{symbol}",
                "x-push_frequency": "once every 100ms",
                "x-response-example": "{\\\"type\\\":\\\"message\\\",\\\"topic\\\":\\\"/market/ticker:BTC-USDT\\\",\\\"subject\\\":\\\"trade.ticker\\\",\\\"data\\\":{\\\"sequence\\\":\\\"1545896668986\\\",\\\"price\\\":\\\"0.08\\\",\\\"size\\\":\\\"0.011\\\",\\\"bestAsk\\\":\\\"0.08\\\",\\\"bestAskSize\\\":\\\"0.18\\\",\\\"bestBid\\\":\\\"0.049\\\",\\\"bestBidSize\\\":\\\"0.036\\\",\\\"Time\\\":1704873323416}}",
                "responses": {
                    "200": {
                        "description": "",
                        "content": {
                            "application/json": {
                                "schema": {
                                    "$ref": "#/components/schemas/Spot_spot_public_ticker"
                                }
                            }
                        }
                    }
                }
            }
        },
        "/allTickers/market/ticker:all": {
            "trace": {
                "summary": "Get All Tickers",
                "deprecated": "false",
                "description": "Subscribe to this topic to get the push of all market symbols BBO change.",
                "tags": [],
                "parameters": [],
                "x-sdk-service": "Spot",
                "x-sdk-sub-service": "spot_public",
                "x-sdk-private": false,
                "x-sdk-method-name": "allTickers",
                "x-topic": "/market/ticker:all",
                "x-push_frequency": "once every 100ms",
                "x-response-example": "{\\\"topic\\\":\\\"/market/ticker:all\\\",\\\"type\\\":\\\"message\\\",\\\"subject\\\":\\\"BTC-USDT\\\",\\\"data\\\":{\\\"bestAsk\\\":\\\"67218.7\\\",\\\"bestAskSize\\\":\\\"1.92318539\\\",\\\"bestBid\\\":\\\"67218.6\\\",\\\"bestBidSize\\\":\\\"0.01045638\\\",\\\"price\\\":\\\"67220\\\",\\\"sequence\\\":\\\"14691455768\\\",\\\"size\\\":\\\"0.00004316\\\",\\\"time\\\":1729757723612}}",
                "responses": {
                    "200": {
                        "description": "",
                        "content": {
                            "application/json": {
                                "schema": {
                                    "$ref": "#/components/schemas/Spot_spot_public_allTickers"
                                }
                            }
                        }
                    }
                }
            }
        },
        "/orderbookLevel1/spotMarket/level1:_symbol_,_symbol_": {
            "trace": {
                "summary": "Orderbook - Level1",
                "deprecated": "false",
                "description": "The system will return the 1 best ask/bid orders data, A topic supports up to 100 symbols. If there is no change in the market, data will not be pushed",
                "tags": [],
                "parameters": [],
                "x-sdk-service": "Spot",
                "x-sdk-sub-service": "spot_public",
                "x-sdk-private": false,
                "x-sdk-method-name": "orderbookLevel1",
                "x-topic": "/spotMarket/level1:{symbol},{symbol}",
                "x-push_frequency": "once every 10ms",
                "x-response-example": "{\\\"topic\\\":\\\"/spotMarket/level1:BTC-USDT\\\",\\\"type\\\":\\\"message\\\",\\\"subject\\\":\\\"level1\\\",\\\"data\\\":{\\\"asks\\\":[\\\"68145.8\\\",\\\"0.51987471\\\"],\\\"bids\\\":[\\\"68145.7\\\",\\\"1.29267802\\\"],\\\"timestamp\\\":1729816058766}}",
                "responses": {
                    "200": {
                        "description": "",
                        "content": {
                            "application/json": {
                                "schema": {
                                    "$ref": "#/components/schemas/Spot_spot_public_orderbookLevel1"
                                }
                            }
                        }
                    }
                }
            }
        },
        "/orderbookLevel5/spotMarket/level2Depth5:_symbol_,_symbol_": {
            "trace": {
                "summary": "Orderbook - Level5",
                "deprecated": "false",
                "description": "The system will return the 5 best ask/bid orders data,A topic supports up to 100 symbols. If there is no change in the market, data will not be pushed",
                "tags": [],
                "parameters": [],
                "x-sdk-service": "Spot",
                "x-sdk-sub-service": "spot_public",
                "x-sdk-private": false,
                "x-sdk-method-name": "orderbookLevel5",
                "x-topic": "/spotMarket/level2Depth5:{symbol},{symbol}",
                "x-push_frequency": "once every 100ms",
                "x-response-example": "{\\\"topic\\\":\\\"/spotMarket/level2Depth5:BTC-USDT\\\",\\\"type\\\":\\\"message\\\",\\\"subject\\\":\\\"level2\\\",\\\"data\\\":{\\\"asks\\\":[[\\\"67996.7\\\",\\\"1.14213262\\\"],[\\\"67996.8\\\",\\\"0.21748212\\\"],[\\\"67996.9\\\",\\\"0.1503747\\\"],[\\\"67997\\\",\\\"0.11446863\\\"],[\\\"67997.1\\\",\\\"0.14842782\\\"]],\\\"bids\\\":[[\\\"67996.6\\\",\\\"0.37969491\\\"],[\\\"67995.3\\\",\\\"0.20779746\\\"],[\\\"67994.5\\\",\\\"0.00047785\\\"],[\\\"67993.4\\\",\\\"0.405\\\"],[\\\"67993.3\\\",\\\"0.13528566\\\"]],\\\"timestamp\\\":1729822226746}}",
                "responses": {
                    "200": {
                        "description": "",
                        "content": {
                            "application/json": {
                                "schema": {
                                    "$ref": "#/components/schemas/Spot_spot_public_orderbookLevel5"
                                }
                            }
                        }
                    }
                }
            }
        },
        "/orderbookLevel50/market/level2:_symbol_,_symbol_": {
            "trace": {
                "summary": "Orderbook - Level50",
                "deprecated": "false",
                "description": "The system will return the 50 best ask/bid orders data, A topic supports up to 100 symbols. If there is no change in the market, data will not be pushed",
                "tags": [],
                "parameters": [],
                "x-sdk-service": "Spot",
                "x-sdk-sub-service": "spot_public",
                "x-sdk-private": false,
                "x-sdk-method-name": "orderbookLevel50",
                "x-topic": "/market/level2:{symbol},{symbol}",
                "x-push_frequency": "once every 100ms",
                "x-response-example": "{\\\"topic\\\":\\\"/spotMarket/level2Depth50:BTC-USDT\\\",\\\"type\\\":\\\"message\\\",\\\"subject\\\":\\\"level2\\\",\\\"data\\\":{\\\"asks\\\":[[\\\"95964.3\\\",\\\"0.08168874\\\"],[\\\"95967.9\\\",\\\"0.00985094\\\"],[\\\"95969.9\\\",\\\"0.00078081\\\"],[\\\"95971.2\\\",\\\"0.10016039\\\"],[\\\"95971.3\\\",\\\"0.12531139\\\"],[\\\"95971.7\\\",\\\"0.00291\\\"],[\\\"95971.9\\\",\\\"0.10271829\\\"],[\\\"95973.3\\\",\\\"0.00021\\\"],[\\\"95974.7\\\",\\\"0.10271829\\\"],[\\\"95976.9\\\",\\\"0.03095177\\\"],[\\\"95977\\\",\\\"0.10271829\\\"],[\\\"95978.7\\\",\\\"0.00022411\\\"],[\\\"95979.1\\\",\\\"0.00023017\\\"],[\\\"95981\\\",\\\"0.00022008\\\"],[\\\"95981.2\\\",\\\"0.14330324\\\"],[\\\"95982.3\\\",\\\"0.27922082\\\"],[\\\"95982.5\\\",\\\"0.02302674\\\"],[\\\"95983.8\\\",\\\"0.00011035\\\"],[\\\"95985\\\",\\\"0.00104222\\\"],[\\\"95985.1\\\",\\\"0.00021808\\\"],[\\\"95985.5\\\",\\\"0.211127\\\"],[\\\"95986.2\\\",\\\"0.09690904\\\"],[\\\"95986.3\\\",\\\"0.31261\\\"],[\\\"95986.9\\\",\\\"0.09225037\\\"],[\\\"95987\\\",\\\"0.01042013\\\"],[\\\"95990.5\\\",\\\"0.12712438\\\"],[\\\"95990.6\\\",\\\"0.0916115\\\"],[\\\"95992.2\\\",\\\"0.279\\\"],[\\\"95992.7\\\",\\\"0.00521084\\\"],[\\\"95995.2\\\",\\\"0.00033\\\"],[\\\"95999.1\\\",\\\"0.02973561\\\"],[\\\"96001.1\\\",\\\"0.083825\\\"],[\\\"96002.6\\\",\\\"0.01900906\\\"],[\\\"96002.7\\\",\\\"0.00041665\\\"],[\\\"96002.8\\\",\\\"0.12531139\\\"],[\\\"96002.9\\\",\\\"0.279\\\"],[\\\"96004.8\\\",\\\"0.02081884\\\"],[\\\"96006.3\\\",\\\"0.00065542\\\"],[\\\"96008.5\\\",\\\"0.00033166\\\"],[\\\"96011\\\",\\\"0.08776246\\\"],[\\\"96012.5\\\",\\\"0.279\\\"],[\\\"96013.3\\\",\\\"0.00066666\\\"],[\\\"96013.9\\\",\\\"0.26097183\\\"],[\\\"96014\\\",\\\"0.01087009\\\"],[\\\"96017\\\",\\\"0.06248892\\\"],[\\\"96017.1\\\",\\\"0.20829641\\\"],[\\\"96022\\\",\\\"0.00107066\\\"],[\\\"96022.1\\\",\\\"0.279\\\"],[\\\"96022.9\\\",\\\"0.0006499\\\"],[\\\"96024.6\\\",\\\"0.00104131\\\"]],\\\"bids\\\":[[\\\"95964.2\\\",\\\"1.35483359\\\"],[\\\"95964.1\\\",\\\"0.01117492\\\"],[\\\"95962.1\\\",\\\"0.0062\\\"],[\\\"95961.8\\\",\\\"0.03081549\\\"],[\\\"95961.7\\\",\\\"0.10271829\\\"],[\\\"95958.5\\\",\\\"0.04681571\\\"],[\\\"95958.4\\\",\\\"0.05177498\\\"],[\\\"95958.2\\\",\\\"0.00155911\\\"],[\\\"95957.8\\\",\\\"0.10271829\\\"],[\\\"95954.7\\\",\\\"0.16312181\\\"],[\\\"95954.6\\\",\\\"0.44102109\\\"],[\\\"95952.6\\\",\\\"0.10271829\\\"],[\\\"95951.3\\\",\\\"0.0062\\\"],[\\\"95951\\\",\\\"0.17075141\\\"],[\\\"95950.9\\\",\\\"0.279\\\"],[\\\"95949.5\\\",\\\"0.13567811\\\"],[\\\"95949.2\\\",\\\"0.05177498\\\"],[\\\"95948.3\\\",\\\"0.10271829\\\"],[\\\"95947.2\\\",\\\"0.04634798\\\"],[\\\"95944.7\\\",\\\"0.10271829\\\"],[\\\"95944.2\\\",\\\"0.05177498\\\"],[\\\"95942.3\\\",\\\"0.26028569\\\"],[\\\"95942.2\\\",\\\"0.10271829\\\"],[\\\"95940.6\\\",\\\"0.12531139\\\"],[\\\"95940.2\\\",\\\"0.43349327\\\"],[\\\"95938.3\\\",\\\"0.01041604\\\"],[\\\"95937.4\\\",\\\"0.04957577\\\"],[\\\"95937.2\\\",\\\"0.00305\\\"],[\\\"95936.3\\\",\\\"0.10271829\\\"],[\\\"95934\\\",\\\"0.05177498\\\"],[\\\"95931.9\\\",\\\"0.03394093\\\"],[\\\"95931.8\\\",\\\"0.10271829\\\"],[\\\"95930\\\",\\\"0.01041814\\\"],[\\\"95927.9\\\",\\\"0.10271829\\\"],[\\\"95927\\\",\\\"0.13312774\\\"],[\\\"95926.9\\\",\\\"0.33077498\\\"],[\\\"95924.9\\\",\\\"0.10271829\\\"],[\\\"95924\\\",\\\"0.00180915\\\"],[\\\"95923.8\\\",\\\"0.00022434\\\"],[\\\"95919.6\\\",\\\"0.00021854\\\"],[\\\"95919.1\\\",\\\"0.01471872\\\"],[\\\"95919\\\",\\\"0.05177498\\\"],[\\\"95918.1\\\",\\\"0.00001889\\\"],[\\\"95917.8\\\",\\\"0.1521089\\\"],[\\\"95917.5\\\",\\\"0.00010962\\\"],[\\\"95916.2\\\",\\\"0.00021958\\\"],[\\\"95915.5\\\",\\\"0.12531139\\\"],[\\\"95915.3\\\",\\\"0.279\\\"],[\\\"95913.6\\\",\\\"0.01739249\\\"],[\\\"95913.5\\\",\\\"0.05177498\\\"]],\\\"timestamp\\\":1733124805073}}",
                "responses": {
                    "200": {
                        "description": "",
                        "content": {
                            "application/json": {
                                "schema": {
                                    "$ref": "#/components/schemas/Spot_spot_public_orderbookLevel50"
                                }
                            }
                        }
                    }
                }
            }
        },
        "/orderbookIncrement/market/level2:_symbol_,_symbol_": {
            "trace": {
                "summary": "Orderbook - Increment",
                "deprecated": "false",
                "description": "The system will return the increment change orderbook data(All depth), A topic supports up to 100 symbols. If there is no change in the market, data will not be pushed",
                "tags": [],
                "parameters": [],
                "x-sdk-service": "Spot",
                "x-sdk-sub-service": "spot_public",
                "x-sdk-private": false,
                "x-sdk-method-name": "orderbookIncrement",
                "x-topic": "/market/level2:{symbol},{symbol}",
                "x-push_frequency": "real-time",
                "x-response-example": "{\\\"topic\\\":\\\"/market/level2:BTC-USDT\\\",\\\"type\\\":\\\"message\\\",\\\"subject\\\":\\\"trade.l2update\\\",\\\"data\\\":{\\\"changes\\\":{\\\"asks\\\":[[\\\"67993.3\\\",\\\"1.21427407\\\",\\\"14701689783\\\"]],\\\"bids\\\":[]},\\\"sequenceEnd\\\":14701689783,\\\"sequenceStart\\\":14701689783,\\\"symbol\\\":\\\"BTC-USDT\\\",\\\"time\\\":1729816425625}}",
                "responses": {
                    "200": {
                        "description": "",
                        "content": {
                            "application/json": {
                                "schema": {
                                    "$ref": "#/components/schemas/Spot_spot_public_orderbookIncrement"
                                }
                            }
                        }
                    }
                }
            }
        },
        "/klines/market/candles:_symbol___type_": {
            "trace": {
                "summary": "Klines",
                "deprecated": "false",
                "description": "Subscribe to this topic to get K-Line data.",
                "tags": [],
                "parameters": [],
                "x-sdk-service": "Spot",
                "x-sdk-sub-service": "spot_public",
                "x-sdk-private": false,
                "x-sdk-method-name": "klines",
                "x-topic": "/market/candles:{symbol}_{type}",
                "x-push_frequency": "real-time",
                "x-response-example": "{\\\"topic\\\":\\\"/market/candles:BTC-USDT_1hour\\\",\\\"type\\\":\\\"message\\\",\\\"subject\\\":\\\"trade.candles.update\\\",\\\"data\\\":{\\\"symbol\\\":\\\"BTC-USDT\\\",\\\"candles\\\":[\\\"1729839600\\\",\\\"67644.9\\\",\\\"67437.6\\\",\\\"67724.8\\\",\\\"67243.8\\\",\\\"44.88321441\\\",\\\"3027558.991928447\\\"],\\\"time\\\":1729842192785164840}}",
                "responses": {
                    "200": {
                        "description": "",
                        "content": {
                            "application/json": {
                                "schema": {
                                    "$ref": "#/components/schemas/Spot_spot_public_klines"
                                }
                            }
                        }
                    }
                }
            }
        },
        "/trade/market/match:_symbol_,_symbol_": {
            "trace": {
                "summary": "Trade",
                "deprecated": "false",
                "description": "Subscribe to this topic to get the matching event data flow of Level 3. A topic supports up to 100 symbols.",
                "tags": [],
                "parameters": [],
                "x-sdk-service": "Spot",
                "x-sdk-sub-service": "spot_public",
                "x-sdk-private": false,
                "x-sdk-method-name": "trade",
                "x-topic": "/market/match:{symbol},{symbol}",
                "x-push_frequency": "real-time",
                "x-response-example": "{\\\"topic\\\":\\\"/market/match:BTC-USDT\\\",\\\"type\\\":\\\"message\\\",\\\"subject\\\":\\\"trade.l3match\\\",\\\"data\\\":{\\\"makerOrderId\\\":\\\"671b5007389355000701b1d3\\\",\\\"price\\\":\\\"67523\\\",\\\"sequence\\\":\\\"11067996711960577\\\",\\\"side\\\":\\\"buy\\\",\\\"size\\\":\\\"0.003\\\",\\\"symbol\\\":\\\"BTC-USDT\\\",\\\"takerOrderId\\\":\\\"671b50161777ff00074c168d\\\",\\\"time\\\":\\\"1729843222921000000\\\",\\\"tradeId\\\":\\\"11067996711960577\\\",\\\"type\\\":\\\"match\\\"}}",
                "responses": {
                    "200": {
                        "description": "",
                        "content": {
                            "application/json": {
                                "schema": {
                                    "$ref": "#/components/schemas/Spot_spot_public_trade"
                                }
                            }
                        }
                    }
                }
            }
        },
        "/symbolSnapshot/market/snapshot:_symbol_": {
            "trace": {
                "summary": "Symbol Snapshot",
                "deprecated": "false",
                "description": "Subscribe to get snapshot data for a single symbol.",
                "tags": [],
                "parameters": [],
                "x-sdk-service": "Spot",
                "x-sdk-sub-service": "spot_public",
                "x-sdk-private": false,
                "x-sdk-method-name": "symbolSnapshot",
                "x-topic": "/market/snapshot:{symbol}",
                "x-push_frequency": "once every 2s",
                "x-response-example": "{\\\"topic\\\":\\\"/market/snapshot:BTC-USDT\\\",\\\"type\\\":\\\"message\\\",\\\"subject\\\":\\\"trade.snapshot\\\",\\\"data\\\":{\\\"sequence\\\":\\\"14691517895\\\",\\\"data\\\":{\\\"askSize\\\":1.15955795,\\\"averagePrice\\\":66867.89967612,\\\"baseCurrency\\\":\\\"BTC\\\",\\\"bidSize\\\":0.81772627,\\\"board\\\":1,\\\"buy\\\":67158.1,\\\"changePrice\\\":315.20000000000000000000,\\\"changeRate\\\":0.0047,\\\"close\\\":67158.1,\\\"datetime\\\":1729758286011,\\\"high\\\":67611.80000000000000000000,\\\"lastTradedPrice\\\":67158.1,\\\"low\\\":65257.10000000000000000000,\\\"makerCoefficient\\\":1.000000,\\\"makerFeeRate\\\":0.001,\\\"marginTrade\\\":true,\\\"mark\\\":0,\\\"market\\\":\\\"USDS\\\",\\\"marketChange1h\\\":{\\\"changePrice\\\":-102.10000000000000000000,\\\"changeRate\\\":-0.0015,\\\"high\\\":67310.60000000000000000000,\\\"low\\\":67051.80000000000000000000,\\\"open\\\":67260.20000000000000000000,\\\"vol\\\":53.73698081000000000000,\\\"volValue\\\":3609965.13819127700000000000},\\\"marketChange24h\\\":{\\\"changePrice\\\":315.20000000000000000000,\\\"changeRate\\\":0.0047,\\\"high\\\":67611.80000000000000000000,\\\"low\\\":65257.10000000000000000000,\\\"open\\\":66842.90000000000000000000,\\\"vol\\\":2227.69895852000000000000,\\\"volValue\\\":147972941.07857507300000000000},\\\"marketChange4h\\\":{\\\"changePrice\\\":-166.30000000000000000000,\\\"changeRate\\\":-0.0024,\\\"high\\\":67476.60000000000000000000,\\\"low\\\":67051.80000000000000000000,\\\"open\\\":67324.40000000000000000000,\\\"vol\\\":173.76971188000000000000,\\\"volValue\\\":11695949.43841656500000000000},\\\"markets\\\":[\\\"USDS\\\",\\\"PoW\\\"],\\\"open\\\":66842.90000000000000000000,\\\"quoteCurrency\\\":\\\"USDT\\\",\\\"sell\\\":67158.2,\\\"siteTypes\\\":[\\\"turkey\\\",\\\"thailand\\\",\\\"global\\\"],\\\"sort\\\":100,\\\"symbol\\\":\\\"BTC-USDT\\\",\\\"symbolCode\\\":\\\"BTC-USDT\\\",\\\"takerCoefficient\\\":1.000000,\\\"takerFeeRate\\\":0.001,\\\"trading\\\":true,\\\"vol\\\":2227.69895852000000000000,\\\"volValue\\\":147972941.07857507300000000000}}}",
                "responses": {
                    "200": {
                        "description": "",
                        "content": {
                            "application/json": {
                                "schema": {
                                    "$ref": "#/components/schemas/Spot_spot_public_symbolSnapshot"
                                }
                            }
                        }
                    }
                }
            }
        },
        "/marketSnapshot/market/snapshot:_market_": {
            "trace": {
                "summary": "Market Snapshot",
                "deprecated": "false",
                "description": "Subscribe this topic to get the snapshot data of for the entire market.",
                "tags": [],
                "parameters": [],
                "x-sdk-service": "Spot",
                "x-sdk-sub-service": "spot_public",
                "x-sdk-private": false,
                "x-sdk-method-name": "marketSnapshot",
                "x-topic": "/market/snapshot:{market}",
                "x-push_frequency": "once every 2s",
                "x-response-example": "{\\\"topic\\\":\\\"/market/snapshot:BTC\\\",\\\"type\\\":\\\"message\\\",\\\"subject\\\":\\\"trade.snapshot\\\",\\\"data\\\":{\\\"sequence\\\":\\\"1729785948015\\\",\\\"data\\\":{\\\"askSize\\\":1375.1096,\\\"averagePrice\\\":0.00000262,\\\"baseCurrency\\\":\\\"CHR\\\",\\\"bidSize\\\":152.0912,\\\"board\\\":0,\\\"buy\\\":0.00000263,\\\"changePrice\\\":0.00000005300000000000,\\\"changeRate\\\":0.0200,\\\"close\\\":0.000002698,\\\"datetime\\\":1729785948008,\\\"high\\\":0.00000274600000000000,\\\"lastTradedPrice\\\":0.000002698,\\\"low\\\":0.00000255800000000000,\\\"makerCoefficient\\\":1.000000,\\\"makerFeeRate\\\":0.001,\\\"marginTrade\\\":false,\\\"mark\\\":0,\\\"market\\\":\\\"BTC\\\",\\\"marketChange1h\\\":{\\\"changePrice\\\":-0.00000000900000000000,\\\"changeRate\\\":-0.0033,\\\"high\\\":0.00000270700000000000,\\\"low\\\":0.00000264200000000000,\\\"open\\\":0.00000270700000000000,\\\"vol\\\":27.10350000000000000000,\\\"volValue\\\":0.00007185015660000000},\\\"marketChange24h\\\":{\\\"changePrice\\\":0.00000005300000000000,\\\"changeRate\\\":0.0200,\\\"high\\\":0.00000274600000000000,\\\"low\\\":0.00000255800000000000,\\\"open\\\":0.00000264500000000000,\\\"vol\\\":6824.94800000000000000000,\\\"volValue\\\":0.01789509649520000000},\\\"marketChange4h\\\":{\\\"changePrice\\\":0.00000000600000000000,\\\"changeRate\\\":0.0022,\\\"high\\\":0.00000270700000000000,\\\"low\\\":0.00000264200000000000,\\\"open\\\":0.00000269200000000000,\\\"vol\\\":92.69020000000000000000,\\\"volValue\\\":0.00024903875740000000},\\\"markets\\\":[\\\"BTC\\\",\\\"DePIN\\\",\\\"Layer 1\\\"],\\\"open\\\":0.00000264500000000000,\\\"quoteCurrency\\\":\\\"BTC\\\",\\\"sell\\\":0.000002695,\\\"siteTypes\\\":[\\\"global\\\"],\\\"sort\\\":100,\\\"symbol\\\":\\\"CHR-BTC\\\",\\\"symbolCode\\\":\\\"CHR-BTC\\\",\\\"takerCoefficient\\\":1.000000,\\\"takerFeeRate\\\":0.001,\\\"trading\\\":true,\\\"vol\\\":6824.94800000000000000000,\\\"volValue\\\":0.01789509649520000000}}}",
                "responses": {
                    "200": {
                        "description": "",
                        "content": {
                            "application/json": {
                                "schema": {
                                    "$ref": "#/components/schemas/Spot_spot_public_marketSnapshot"
                                }
                            }
                        }
                    }
                }
            }
        }
    },
    "components": {
        "schemas": {
            "Spot_spot_public_ticker": {
                "type": "object",
                "properties": {
                    "type": {
                        "type": "string"
                    },
                    "topic": {
                        "type": "string"
                    },
                    "subject": {
                        "type": "string"
                    },
                    "data": {
                        "type": "object",
                        "properties": {
                            "sequence": {
                                "description": "Sequence number",
                                "type": "string"
                            },
                            "price": {
                                "description": "Last traded price",
                                "type": "string"
                            },
                            "size": {
                                "description": "Last traded amount",
                                "type": "string"
                            },
                            "bestAsk": {
                                "description": "Best ask price",
                                "type": "string"
                            },
                            "bestAskSize": {
                                "description": "Best ask size",
                                "type": "string"
                            },
                            "bestBid": {
                                "description": "Best bid price",
                                "type": "string"
                            },
                            "bestBidSize": {
                                "description": "Best bid size",
                                "type": "string"
                            },
                            "Time": {
                                "type": "integer",
                                "description": "The matching time of the latest transaction",
                                "format": "int64"
                            }
                        },
                        "required": [
                            "sequence",
                            "price",
                            "size",
                            "bestAsk",
                            "bestAskSize",
                            "bestBid",
                            "bestBidSize",
                            "Time"
                        ]
                    }
                },
                "required": [
                    "type",
                    "topic",
                    "subject",
                    "data"
                ],
                "x-apidog-refs": {}
            },
            "Spot_spot_public_allTickers": {
                "type": "object",
                "properties": {
                    "topic": {
                        "type": "string"
                    },
                    "type": {
                        "type": "string"
                    },
                    "subject": {
                        "type": "string"
                    },
                    "data": {
                        "type": "object",
                        "properties": {
                            "bestAsk": {
                                "type": "string"
                            },
                            "bestAskSize": {
                                "type": "string"
                            },
                            "bestBid": {
                                "type": "string"
                            },
                            "bestBidSize": {
                                "type": "string"
                            },
                            "price": {
                                "type": "string"
                            },
                            "sequence": {
                                "type": "string"
                            },
                            "size": {
                                "type": "string"
                            },
                            "time": {
                                "type": "integer",
                                "description": "The matching time of the latest transaction",
                                "format": "int64"
                            }
                        },
                        "required": [
                            "bestAsk",
                            "bestAskSize",
                            "bestBid",
                            "bestBidSize",
                            "price",
                            "sequence",
                            "size",
                            "time"
                        ]
                    }
                },
                "required": [
                    "topic",
                    "type",
                    "subject",
                    "data"
                ]
            },
            "Spot_spot_public_orderbookLevel1": {
                "type": "object",
                "properties": {
                    "topic": {
                        "type": "string"
                    },
                    "type": {
                        "type": "string"
                    },
                    "subject": {
                        "type": "string"
                    },
                    "data": {
                        "type": "object",
                        "properties": {
                            "asks": {
                                "type": "array",
                                "items": {
                                    "type": "string"
                                },
                                "description": "price, size"
                            },
                            "bids": {
                                "type": "array",
                                "items": {
                                    "type": "string"
                                }
                            },
                            "timestamp": {
                                "type": "integer",
                                "format": "int64"
                            }
                        },
                        "required": [
                            "asks",
                            "bids",
                            "timestamp"
                        ]
                    }
                },
                "required": [
                    "topic",
                    "type",
                    "subject",
                    "data"
                ]
            },
            "Spot_spot_public_orderbookLevel5": {
                "type": "object",
                "properties": {
                    "topic": {
                        "type": "string"
                    },
                    "type": {
                        "type": "string"
                    },
                    "subject": {
                        "type": "string"
                    },
                    "data": {
                        "type": "object",
                        "properties": {
                            "asks": {
                                "type": "array",
                                "items": {
                                    "type": "array",
                                    "items": {
                                        "type": "string"
                                    }
                                },
                                "description": "price, size"
                            },
                            "bids": {
                                "type": "array",
                                "items": {
                                    "type": "array",
                                    "items": {
                                        "type": "string"
                                    }
                                }
                            },
                            "timestamp": {
                                "type": "integer",
                                "format": "int64"
                            }
                        },
                        "required": [
                            "asks",
                            "bids",
                            "timestamp"
                        ]
                    }
                },
                "required": [
                    "topic",
                    "type",
                    "subject",
                    "data"
                ]
            },
            "Spot_spot_public_orderbookLevel50": {
                "type": "object",
                "properties": {
                    "type": {
                        "type": "string"
                    },
                    "topic": {
                        "type": "string"
                    },
                    "subject": {
                        "type": "string"
                    },
                    "data": {
                        "type": "object",
                        "properties": {
                            "changes": {
                                "type": "object",
                                "properties": {
                                    "asks": {
                                        "type": "array",
                                        "items": {
                                            "type": "array",
                                            "items": {
                                                "type": "string"
                                            }
                                        }
                                    },
                                    "bids": {
                                        "type": "array",
                                        "items": {
                                            "type": "array",
                                            "items": {
                                                "type": "string"
                                            }
                                        }
                                    }
                                },
                                "required": [
                                    "asks",
                                    "bids"
                                ]
                            },
                            "sequenceEnd": {
                                "type": "integer",
                                "format": "int64"
                            },
                            "sequenceStart": {
                                "type": "integer",
                                "format": "int64"
                            },
                            "symbol": {
                                "type": "string"
                            },
                            "time": {
                                "type": "integer",
                                "format": "int64"
                            }
                        },
                        "required": [
                            "changes",
                            "sequenceEnd",
                            "sequenceStart",
                            "symbol",
                            "time"
                        ]
                    }
                },
                "required": [
                    "type",
                    "topic",
                    "subject",
                    "data"
                ]
            },
            "Spot_spot_public_orderbookIncrement": {
                "type": "object",
                "properties": {
                    "topic": {
                        "type": "string"
                    },
                    "type": {
                        "type": "string"
                    },
                    "subject": {
                        "type": "string"
                    },
                    "data": {
                        "type": "object",
                        "properties": {
                            "changes": {
                                "type": "object",
                                "properties": {
                                    "asks": {
                                        "type": "array",
                                        "items": {
                                            "type": "array",
                                            "items": {
                                                "type": "string"
                                            }
                                        },
                                        "description": "price,size,sequence"
                                    },
                                    "bids": {
                                        "type": "array",
                                        "items": {
                                            "type": "array",
                                            "items": {
                                                "type": "string"
                                            }
                                        }
                                    }
                                },
                                "required": [
                                    "asks",
                                    "bids"
                                ]
                            },
                            "sequenceEnd": {
                                "type": "integer",
                                "format": "int64"
                            },
                            "sequenceStart": {
                                "type": "integer",
                                "format": "int64"
                            },
                            "symbol": {
                                "type": "string"
                            },
                            "time": {
                                "type": "integer",
                                "description": "milliseconds",
                                "format": "int64"
                            }
                        },
                        "required": [
                            "changes",
                            "sequenceEnd",
                            "sequenceStart",
                            "symbol",
                            "time"
                        ]
                    }
                },
                "required": [
                    "topic",
                    "type",
                    "subject",
                    "data"
                ]
            },
            "Spot_spot_public_klines": {
                "type": "object",
                "properties": {
                    "topic": {
                        "type": "string"
                    },
                    "type": {
                        "type": "string"
                    },
                    "subject": {
                        "type": "string"
                    },
                    "data": {
                        "type": "object",
                        "properties": {
                            "symbol": {
                                "type": "string",
                                "description": "symbol"
                            },
                            "candles": {
                                "type": "array",
                                "items": {
                                    "type": "string"
                                },
                                "description": "Start time of the candle cycle,open price,close price, high price,low price,Transaction volume,Transaction amount"
                            },
                            "time": {
                                "type": "integer",
                                "description": "now（us）",
                                "format": "int64"
                            }
                        },
                        "required": [
                            "symbol",
                            "candles",
                            "time"
                        ]
                    }
                },
                "required": [
                    "topic",
                    "type",
                    "subject",
                    "data"
                ]
            },
            "Spot_spot_public_trade": {
                "type": "object",
                "properties": {
                    "topic": {
                        "type": "string"
                    },
                    "type": {
                        "type": "string"
                    },
                    "subject": {
                        "type": "string"
                    },
                    "data": {
                        "type": "object",
                        "properties": {
                            "makerOrderId": {
                                "type": "string"
                            },
                            "price": {
                                "type": "string"
                            },
                            "sequence": {
                                "type": "string"
                            },
                            "side": {
                                "type": "string"
                            },
                            "size": {
                                "type": "string"
                            },
                            "symbol": {
                                "type": "string"
                            },
                            "takerOrderId": {
                                "type": "string"
                            },
                            "time": {
                                "type": "string"
                            },
                            "tradeId": {
                                "type": "string"
                            },
                            "type": {
                                "type": "string"
                            }
                        },
                        "required": [
                            "makerOrderId",
                            "price",
                            "sequence",
                            "side",
                            "size",
                            "symbol",
                            "takerOrderId",
                            "time",
                            "tradeId",
                            "type"
                        ]
                    }
                },
                "required": [
                    "topic",
                    "type",
                    "subject",
                    "data"
                ]
            },
            "Spot_spot_public_symbolSnapshot": {
                "type": "object",
                "properties": {
                    "topic": {
                        "type": "string"
                    },
                    "type": {
                        "type": "string"
                    },
                    "subject": {
                        "type": "string"
                    },
                    "data": {
                        "type": "object",
                        "properties": {
                            "sequence": {
                                "type": "string"
                            },
                            "data": {
                                "type": "object",
                                "properties": {
                                    "askSize": {
                                        "type": "number"
                                    },
                                    "averagePrice": {
                                        "type": "number"
                                    },
                                    "baseCurrency": {
                                        "type": "string"
                                    },
                                    "bidSize": {
                                        "type": "number"
                                    },
                                    "board": {
                                        "type": "integer",
                                        "description": "Trading pair partition： 0.primary partition 1.KuCoin Plus\", example = \"1\"",
                                        "enum": [
                                            0,
                                            1
                                        ],
                                        "x-api-enum": [
                                            {
                                                "value": 0,
                                                "name": "",
                                                "description": "primary partition"
                                            },
                                            {
                                                "value": 1,
                                                "name": "",
                                                "description": "KuCoin Plus"
                                            }
                                        ]
                                    },
                                    "buy": {
                                        "type": "number"
                                    },
                                    "changePrice": {
                                        "type": "number"
                                    },
                                    "changeRate": {
                                        "type": "number"
                                    },
                                    "close": {
                                        "type": "number"
                                    },
                                    "datetime": {
                                        "type": "integer",
                                        "format": "int64"
                                    },
                                    "high": {
                                        "type": "number"
                                    },
                                    "lastTradedPrice": {
                                        "type": "number"
                                    },
                                    "low": {
                                        "type": "number"
                                    },
                                    "makerCoefficient": {
                                        "type": "number"
                                    },
                                    "makerFeeRate": {
                                        "type": "number"
                                    },
                                    "marginTrade": {
                                        "type": "boolean"
                                    },
                                    "mark": {
                                        "type": "integer",
                                        "description": "Trading Pair Mark： 0.default 1.ST. 2.NEW\", example = \"1\"",
                                        "enum": [
                                            0,
                                            1,
                                            2
                                        ],
                                        "x-api-enum": [
                                            {
                                                "value": 0,
                                                "name": "",
                                                "description": "default"
                                            },
                                            {
                                                "value": 1,
                                                "name": "",
                                                "description": "ST"
                                            },
                                            {
                                                "value": 2,
                                                "name": "",
                                                "description": "NEW"
                                            }
                                        ]
                                    },
                                    "market": {
                                        "type": "string"
                                    },
                                    "marketChange1h": {
                                        "type": "object",
                                        "properties": {
                                            "changePrice": {
                                                "type": "number"
                                            },
                                            "changeRate": {
                                                "type": "number"
                                            },
                                            "high": {
                                                "type": "number"
                                            },
                                            "low": {
                                                "type": "number"
                                            },
                                            "open": {
                                                "type": "number"
                                            },
                                            "vol": {
                                                "type": "number"
                                            },
                                            "volValue": {
                                                "type": "number"
                                            }
                                        },
                                        "required": [
                                            "changePrice",
                                            "changeRate",
                                            "high",
                                            "low",
                                            "open",
                                            "vol",
                                            "volValue"
                                        ]
                                    },
                                    "marketChange24h": {
                                        "type": "object",
                                        "properties": {
                                            "changePrice": {
                                                "type": "number"
                                            },
                                            "changeRate": {
                                                "type": "number"
                                            },
                                            "high": {
                                                "type": "number"
                                            },
                                            "low": {
                                                "type": "number"
                                            },
                                            "open": {
                                                "type": "number"
                                            },
                                            "vol": {
                                                "type": "number"
                                            },
                                            "volValue": {
                                                "type": "number"
                                            }
                                        },
                                        "required": [
                                            "changePrice",
                                            "changeRate",
                                            "high",
                                            "low",
                                            "open",
                                            "vol",
                                            "volValue"
                                        ]
                                    },
                                    "marketChange4h": {
                                        "type": "object",
                                        "properties": {
                                            "changePrice": {
                                                "type": "number"
                                            },
                                            "changeRate": {
                                                "type": "number"
                                            },
                                            "high": {
                                                "type": "number"
                                            },
                                            "low": {
                                                "type": "number"
                                            },
                                            "open": {
                                                "type": "number"
                                            },
                                            "vol": {
                                                "type": "number"
                                            },
                                            "volValue": {
                                                "type": "number"
                                            }
                                        },
                                        "required": [
                                            "changePrice",
                                            "changeRate",
                                            "high",
                                            "low",
                                            "open",
                                            "vol",
                                            "volValue"
                                        ]
                                    },
                                    "markets": {
                                        "type": "array",
                                        "items": {
                                            "type": "string"
                                        }
                                    },
                                    "open": {
                                        "type": "number"
                                    },
                                    "quoteCurrency": {
                                        "type": "string"
                                    },
                                    "sell": {
                                        "type": "number"
                                    },
                                    "siteTypes": {
                                        "type": "array",
                                        "items": {
                                            "type": "string"
                                        }
                                    },
                                    "sort": {
                                        "type": "integer",
                                        "description": "sorting number(Pointless)"
                                    },
                                    "symbol": {
                                        "type": "string"
                                    },
                                    "symbolCode": {
                                        "type": "string"
                                    },
                                    "takerCoefficient": {
                                        "type": "number"
                                    },
                                    "takerFeeRate": {
                                        "type": "number"
                                    },
                                    "trading": {
                                        "type": "boolean"
                                    },
                                    "vol": {
                                        "type": "number"
                                    },
                                    "volValue": {
                                        "type": "number",
                                        "description": "24-hour rolling transaction volume, refreshed every 2s"
                                    }
                                },
                                "required": [
                                    "askSize",
                                    "averagePrice",
                                    "baseCurrency",
                                    "bidSize",
                                    "board",
                                    "buy",
                                    "changePrice",
                                    "changeRate",
                                    "close",
                                    "datetime",
                                    "high",
                                    "lastTradedPrice",
                                    "low",
                                    "makerCoefficient",
                                    "makerFeeRate",
                                    "marginTrade",
                                    "mark",
                                    "market",
                                    "marketChange1h",
                                    "marketChange24h",
                                    "marketChange4h",
                                    "markets",
                                    "open",
                                    "quoteCurrency",
                                    "sell",
                                    "siteTypes",
                                    "sort",
                                    "symbol",
                                    "symbolCode",
                                    "takerCoefficient",
                                    "takerFeeRate",
                                    "trading",
                                    "vol",
                                    "volValue"
                                ]
                            }
                        },
                        "required": [
                            "sequence",
                            "data"
                        ]
                    }
                },
                "required": [
                    "topic",
                    "type",
                    "subject",
                    "data"
                ]
            },
            "Spot_spot_public_marketSnapshot": {
                "type": "object",
                "properties": {
                    "topic": {
                        "type": "string"
                    },
                    "type": {
                        "type": "string"
                    },
                    "subject": {
                        "type": "string"
                    },
                    "data": {
                        "type": "object",
                        "properties": {
                            "sequence": {
                                "type": "string"
                            },
                            "data": {
                                "type": "object",
                                "properties": {
                                    "askSize": {
                                        "type": "number"
                                    },
                                    "averagePrice": {
                                        "type": "number"
                                    },
                                    "baseCurrency": {
                                        "type": "string"
                                    },
                                    "bidSize": {
                                        "type": "number"
                                    },
                                    "board": {
                                        "type": "integer",
                                        "description": "Trading pair partition： 0.primary partition 1.KuCoin Plus\", example = \"1\"",
                                        "enum": [
                                            0,
                                            1
                                        ],
                                        "x-api-enum": [
                                            {
                                                "value": 0,
                                                "name": "",
                                                "description": "primary partition"
                                            },
                                            {
                                                "value": 1,
                                                "name": "",
                                                "description": "KuCoin Plus"
                                            }
                                        ],
                                        "example": [
                                            1
                                        ]
                                    },
                                    "buy": {
                                        "type": "number"
                                    },
                                    "changePrice": {
                                        "type": "number"
                                    },
                                    "changeRate": {
                                        "type": "number"
                                    },
                                    "close": {
                                        "type": "number"
                                    },
                                    "datetime": {
                                        "type": "integer",
                                        "format": "int64"
                                    },
                                    "high": {
                                        "type": "number"
                                    },
                                    "lastTradedPrice": {
                                        "type": "number"
                                    },
                                    "low": {
                                        "type": "number"
                                    },
                                    "makerCoefficient": {
                                        "type": "number"
                                    },
                                    "makerFeeRate": {
                                        "type": "number"
                                    },
                                    "marginTrade": {
                                        "type": "boolean"
                                    },
                                    "mark": {
                                        "type": "integer",
                                        "description": "Trading Pair Mark： 0.default 1.ST. 2.NEW\", example = \"1\"",
                                        "enum": [
                                            0,
                                            1,
                                            2
                                        ],
                                        "x-api-enum": [
                                            {
                                                "value": 0,
                                                "name": "",
                                                "description": "default "
                                            },
                                            {
                                                "value": 1,
                                                "name": "",
                                                "description": "ST"
                                            },
                                            {
                                                "value": 2,
                                                "name": "",
                                                "description": "NEW"
                                            }
                                        ],
                                        "example": [
                                            1
                                        ]
                                    },
                                    "market": {
                                        "type": "string"
                                    },
                                    "marketChange1h": {
                                        "type": "object",
                                        "properties": {
                                            "changePrice": {
                                                "type": "number"
                                            },
                                            "changeRate": {
                                                "type": "number"
                                            },
                                            "high": {
                                                "type": "number"
                                            },
                                            "low": {
                                                "type": "number"
                                            },
                                            "open": {
                                                "type": "number"
                                            },
                                            "vol": {
                                                "type": "number"
                                            },
                                            "volValue": {
                                                "type": "number"
                                            }
                                        },
                                        "required": [
                                            "changePrice",
                                            "changeRate",
                                            "high",
                                            "low",
                                            "open",
                                            "vol",
                                            "volValue"
                                        ]
                                    },
                                    "marketChange24h": {
                                        "type": "object",
                                        "properties": {
                                            "changePrice": {
                                                "type": "number"
                                            },
                                            "changeRate": {
                                                "type": "number"
                                            },
                                            "high": {
                                                "type": "number"
                                            },
                                            "low": {
                                                "type": "number"
                                            },
                                            "open": {
                                                "type": "number"
                                            },
                                            "vol": {
                                                "type": "number"
                                            },
                                            "volValue": {
                                                "type": "number"
                                            }
                                        },
                                        "required": [
                                            "changePrice",
                                            "changeRate",
                                            "high",
                                            "low",
                                            "open",
                                            "vol",
                                            "volValue"
                                        ]
                                    },
                                    "marketChange4h": {
                                        "type": "object",
                                        "properties": {
                                            "changePrice": {
                                                "type": "number"
                                            },
                                            "changeRate": {
                                                "type": "number"
                                            },
                                            "high": {
                                                "type": "number"
                                            },
                                            "low": {
                                                "type": "number"
                                            },
                                            "open": {
                                                "type": "number"
                                            },
                                            "vol": {
                                                "type": "number"
                                            },
                                            "volValue": {
                                                "type": "number"
                                            }
                                        },
                                        "required": [
                                            "changePrice",
                                            "changeRate",
                                            "high",
                                            "low",
                                            "open",
                                            "vol",
                                            "volValue"
                                        ]
                                    },
                                    "markets": {
                                        "type": "array",
                                        "items": {
                                            "type": "string"
                                        }
                                    },
                                    "open": {
                                        "type": "number"
                                    },
                                    "quoteCurrency": {
                                        "type": "string"
                                    },
                                    "sell": {
                                        "type": "number"
                                    },
                                    "siteTypes": {
                                        "type": "array",
                                        "items": {
                                            "type": "string"
                                        }
                                    },
                                    "sort": {
                                        "type": "integer",
                                        "description": "sorting number"
                                    },
                                    "symbol": {
                                        "type": "string"
                                    },
                                    "symbolCode": {
                                        "type": "string"
                                    },
                                    "takerCoefficient": {
                                        "type": "number"
                                    },
                                    "takerFeeRate": {
                                        "type": "number"
                                    },
                                    "trading": {
                                        "type": "boolean"
                                    },
                                    "vol": {
                                        "type": "number"
                                    },
                                    "volValue": {
                                        "type": "number"
                                    }
                                },
                                "required": [
                                    "askSize",
                                    "averagePrice",
                                    "baseCurrency",
                                    "bidSize",
                                    "board",
                                    "buy",
                                    "changePrice",
                                    "changeRate",
                                    "close",
                                    "datetime",
                                    "high",
                                    "lastTradedPrice",
                                    "low",
                                    "makerCoefficient",
                                    "makerFeeRate",
                                    "marginTrade",
                                    "mark",
                                    "market",
                                    "marketChange1h",
                                    "marketChange24h",
                                    "marketChange4h",
                                    "markets",
                                    "open",
                                    "quoteCurrency",
                                    "sell",
                                    "siteTypes",
                                    "sort",
                                    "symbol",
                                    "symbolCode",
                                    "takerCoefficient",
                                    "takerFeeRate",
                                    "trading",
                                    "vol",
                                    "volValue"
                                ]
                            }
                        },
                        "required": [
                            "sequence",
                            "data"
                        ]
                    }
                },
                "required": [
                    "topic",
                    "type",
                    "subject",
                    "data"
                ]
            }
        }
    }
}